spritely/__init__.py
spritely/cli.py
spritely-0.0.1.dist-info/licenses/LICENSE
spritely-0.0.1.dist-info/METADATA
spritely-0.0.1.dist-info/WHEEL
spritely-0.0.1.dist-info/entry_points.txt
spritely-0.0.1.dist-info/top_level.txt
spritely-0.0.1.dist-info/RECORD
