Metadata-Version: 2.4
Name: spritely
Version: 0.0.1
Summary: Generate an svg sprite file from other svg files
License-Expression: GPL-2.0
Project-URL: Homepage, https://github.com/marbex7/spritely
Project-URL: Issues, https://github.com/marbex7/spritely/issues
Requires-Python: >=3.11
License-File: LICENSE
Requires-Dist: attrs
Requires-Dist: click
Requires-Dist: PyYAML
Dynamic: license-file
